tree_html/__init__.py
tree_html/build_input.py
tree_html/parse.py
tree_html/render_assets.py
tree_html/run.py
tree_html/utils.py
tree_html/assets/__init__.py
tree_html/assets/cd-icons.svg
tree_html/assets/main.js
tree_html/assets/stylesheet-blue-theme.css
tree_html/assets/stylesheet-grey-theme.css
tree_html/assets/util.js
tree_html/templates/index.html
tree_html-1.1.2.dist-info/LICENSE
tree_html-1.1.2.dist-info/METADATA
tree_html-1.1.2.dist-info/WHEEL
tree_html-1.1.2.dist-info/entry_points.txt
tree_html-1.1.2.dist-info/top_level.txt
tree_html-1.1.2.dist-info/RECORD
