Metadata-Version: 2.1
Name: tree-html
Version: 1.1.2
Summary: Renders an interactive directory structure in html from a local path on disk
Home-page: http://ghe-rss.roche.com/todtd/interactive-directory-structure.git
Author: todtd
Author-email: davis.todt@roche.com
License: UNKNOWN
Platform: UNKNOWN
Classifier: Programming Language :: Python :: 3
Classifier: License :: OSI Approved :: MIT License
Classifier: Operating System :: MacOS :: MacOS X
Requires-Dist: click
Requires-Dist: jinja2
